skill_ovos_fallback_dialogpt/LICENSE
skill_ovos_fallback_dialogpt/MANIFEST.in
skill_ovos_fallback_dialogpt/README.md
skill_ovos_fallback_dialogpt/__init__.py
skill_ovos_fallback_dialogpt/version.py
skill_ovos_fallback_dialogpt/skill_ovos_fallback_dialogpt.egg-info/PKG-INFO
skill_ovos_fallback_dialogpt/skill_ovos_fallback_dialogpt.egg-info/SOURCES.txt
skill_ovos_fallback_dialogpt/skill_ovos_fallback_dialogpt.egg-info/dependency_links.txt
skill_ovos_fallback_dialogpt/skill_ovos_fallback_dialogpt.egg-info/entry_points.txt
skill_ovos_fallback_dialogpt/skill_ovos_fallback_dialogpt.egg-info/requires.txt
skill_ovos_fallback_dialogpt/skill_ovos_fallback_dialogpt.egg-info/top_level.txt
skill_ovos_fallback_dialogpt-0.0.0a1.dist-info/LICENSE
skill_ovos_fallback_dialogpt-0.0.0a1.dist-info/METADATA
skill_ovos_fallback_dialogpt-0.0.0a1.dist-info/WHEEL
skill_ovos_fallback_dialogpt-0.0.0a1.dist-info/entry_points.txt
skill_ovos_fallback_dialogpt-0.0.0a1.dist-info/top_level.txt
skill_ovos_fallback_dialogpt-0.0.0a1.dist-info/RECORD
