Metadata-Version: 2.1
Name: skill-ovos-fallback-dialogpt
Version: 0.0.0a1
Summary: ovos DialoGPT skill
Home-page: https://github.com/OpenVoiceOS/skill-ovos-fallback-dialogpt
Author: JarbasAi
Author-email: jarbasai@mailfence.com
License: Apache-2.0
Keywords: ovos skill plugin
Platform: UNKNOWN
Requires-Dist: ovos-solver-dialogpt-plugin
Requires-Dist: ovos-utils (>=0.0.28,~=0.0)
Requires-Dist: ovos-workshop (>=0.0.11,~=0.0)
